{
  "navMain": [
    {
      "title": "Dashboard",
      "url": "/admin",
      "icon": "dashboard"
    },
    {
      "title": "Content",
      "url": "/admin/content",
      "icon": "post",
      "items": [
        { "title": "All Posts", "url": "/admin/content/posts" },
        { "title": "New Post", "url": "/admin/content/new" },
        { "title": "Categories", "url": "/admin/content/categories" },
        { "title": "Tags", "url": "/admin/content/tags" }
      ]
    },
    {
      "title": "Media",
      "url": "/admin/media",
      "icon": "image",
      "items": [
        { "title": "Library", "url": "/admin/media/library" },
        { "title": "Upload", "url": "/admin/media/upload" }
      ]
    },
    {
      "title": "Users",
      "url": "/admin/users",
      "icon": "people",
      "items": [
        { "title": "All Users", "url": "/admin/users" },
        { "title": "Add New", "url": "/admin/users/new" },
        { "title": "Roles", "url": "/admin/users/roles" }
      ]
    },
    {
      "title": "Comments",
      "url": "/admin/comments",
      "icon": "comment"
    }, 
    {
      "title": "Analytics",
      "url": "/admin/analytics",
      "icon": "analytics",
      "items": [
        { "title": "Overview", "url": "/admin/analytics" },
        { "title": "Traffic", "url": "/admin/analytics/traffic" },
        { "title": "Popular Content", "url": "/admin/analytics/popular" }
      ]
    }
  ]
}